elasticsearch_metrics/__init__.py
elasticsearch_metrics/exceptions.py
elasticsearch_metrics/factory.py
elasticsearch_metrics/field.py
elasticsearch_metrics/metrics.py
elasticsearch_metrics/registry.py
elasticsearch_metrics/signals.py
elasticsearch_metrics/management/__init__.py
elasticsearch_metrics/management/color.py
elasticsearch_metrics/management/commands/__init__.py
elasticsearch_metrics/management/commands/check_metrics.py
elasticsearch_metrics/management/commands/show_metrics.py
elasticsearch_metrics/management/commands/sync_metrics.py
tests/dummyapp/__init__.py
tests/dummyapp/apps.py
tests/dummyapp/metrics.py
tests/dummyapp/models.py
tests/test_management_commands/__init__.py
tests/test_management_commands/test_check_metrics.py
tests/test_management_commands/test_show_metrics.py
tests/test_management_commands/test_sync_metrics.py
django_elasticsearch_metrics-5.0.0.dist-info/LICENSE
django_elasticsearch_metrics-5.0.0.dist-info/METADATA
django_elasticsearch_metrics-5.0.0.dist-info/WHEEL
django_elasticsearch_metrics-5.0.0.dist-info/top_level.txt
django_elasticsearch_metrics-5.0.0.dist-info/RECORD
