Metadata-Version: 2.1
Name: django-elasticsearch-metrics
Version: 5.0.0
Summary: Django app for storing time-series metrics in Elasticsearch.
Home-page: http://github.com/CenterForOpenScience/django-elasticsearch-metrics
Author: Steven Loria, Dawn Pattison
Author-email: steve@cos.io, pattison.dawn@cos.io
License: MIT
Project-URL: Issues, https://github.com/CenterForOpenScience/django-elasticsearch-metrics/issues
Project-URL: Changelog, https://github.com/CenterForOpenScience/django-elasticsearch-metrics/blob/master/CHANGELOG.md
Keywords: django,elastic,elasticsearch,elasticsearch-dsl,time-series,metrics,statistics
Platform: UNKNOWN
Classifier: Operating System :: OS Independent
Classifier: Programming Language :: Python
Classifier: Programming Language :: Python :: 2
Classifier: Programming Language :: Python :: 2.7
Classifier: Programming Language :: Python :: 3
Classifier: Programming Language :: Python :: 3.5
Classifier: Programming Language :: Python :: 3.6
Classifier: Programming Language :: Python :: 3.7
Classifier: Framework :: Django
Classifier: Framework :: Django :: 1.11
Classifier: Framework :: Django :: 2.0
Classifier: Environment :: Web Environment
Classifier: Intended Audience :: Developers
Classifier: Topic :: Internet :: WWW/HTTP
Classifier: Topic :: Software Development :: Libraries :: Python Modules
Requires-Dist: elasticsearch-dsl (<6.3.0,>=6.0.0)
Provides-Extra: dev
Requires-Dist: pytest ; extra == 'dev'
Requires-Dist: mock ; extra == 'dev'
Requires-Dist: pytest-django (==3.4.4) ; extra == 'dev'
Requires-Dist: factory-boy (==2.11.1) ; extra == 'dev'
Requires-Dist: flake8 (==3.6.0) ; extra == 'dev'
Requires-Dist: pre-commit (==1.12.0) ; extra == 'dev'
Requires-Dist: konch ; extra == 'dev'
Requires-Dist: tox ; extra == 'dev'
Requires-Dist: flake8-bugbear (==18.8.0) ; (python_version >= "3.5") and extra == 'dev'
Provides-Extra: lint
Requires-Dist: flake8 (==3.6.0) ; extra == 'lint'
Requires-Dist: pre-commit (==1.12.0) ; extra == 'lint'
Requires-Dist: flake8-bugbear (==18.8.0) ; (python_version >= "3.5") and extra == 'lint'
Provides-Extra: tests
Requires-Dist: pytest ; extra == 'tests'
Requires-Dist: mock ; extra == 'tests'
Requires-Dist: pytest-django (==3.4.4) ; extra == 'tests'
Requires-Dist: factory-boy (==2.11.1) ; extra == 'tests'
